cmdllm/__init__.py
cmdllm/cli.py
cmdllm/command_executor.py
cmdllm/config.py
cmdllm/context_manager.py
cmdllm/llm_processor.py
cmdllm-0.1.2.dist-info/licenses/LICENSE
cmdllm-0.1.2.dist-info/METADATA
cmdllm-0.1.2.dist-info/WHEEL
cmdllm-0.1.2.dist-info/entry_points.txt
cmdllm-0.1.2.dist-info/top_level.txt
cmdllm-0.1.2.dist-info/RECORD
