Metadata-Version: 2.4
Name: cmdllm
Version: 0.1.2
Summary: Use natural language to operate all command-line tools
Home-page: https://github.com/yexia553/cmdllm
Author: Zhixiang Pan
Author-email: Zhixiang Pan <pzx553@gmail.com>
License: MIT
Project-URL: Homepage, https://github.com/yexia553/cmdllm
Project-URL: Bug Tracker, https://github.com/yexia553/cmdllm/issues
Keywords: cli,command-line,llm,ai
Classifier: Programming Language :: Python :: 3
Classifier: License :: OSI Approved :: Apache Software License
Classifier: Operating System :: OS Independent
Requires-Python: >=3.6
License-File: LICENSE
Requires-Dist: click>=8.1.0
Requires-Dist: pyyaml>=6.0
Requires-Dist: openai>=1.0.0
Dynamic: author
Dynamic: home-page
Dynamic: license-file
Dynamic: requires-python
